gpctools/__init__.py
gpctools/decorators/__init__.py
gpctools/decorators/exectime.py
gpctools/generic/__init__.py
gpctools/generic/list_get.py
gpctools-0.1.8.dist-info/METADATA
gpctools-0.1.8.dist-info/WHEEL
gpctools-0.1.8.dist-info/top_level.txt
gpctools-0.1.8.dist-info/RECORD
