Metadata-Version: 2.1
Name: gpctools
Version: 0.1.8
Summary: Python package for common use tools
Home-page: https://github.com/danbarml/gpctools
Author: Danilo B. M. de Lima
Author-email: d.lima@gp-joule.de
Classifier: Programming Language :: Python :: 3
Classifier: License :: OSI Approved :: MIT License
Classifier: Operating System :: OS Independent
Requires-Python: >=3.11
